<annotation>
	<folder></folder>
	<filename>0172_jpg.rf.b2184460bd988c9d24fe4407daaa608c.jpg</filename>
	<path>0172_jpg.rf.b2184460bd988c9d24fe4407daaa608c.jpg</path>
	<source>
		<database>roboflow.ai</database>
	</source>
	<size>
		<width>300</width>
		<height>300</height>
		<depth>3</depth>
	</size>
	<segmented>0</segmented>
	<object>
		<name>car</name>
		<pose>Unspecified</pose>
		<truncated>0</truncated>
		<difficult>0</difficult>
		<occluded>0</occluded>
		<bndbox>
			<xmin>132</xmin>
			<xmax>184</xmax>
			<ymin>27</ymin>
			<ymax>48</ymax>
		</bndbox>
	</object>
</annotation>
