<annotation>
	<folder></folder>
	<filename>0250_jpg.rf.de8a85879438b98ccf02afa757b7d5ac.jpg</filename>
	<path>0250_jpg.rf.de8a85879438b98ccf02afa757b7d5ac.jpg</path>
	<source>
		<database>roboflow.ai</database>
	</source>
	<size>
		<width>300</width>
		<height>300</height>
		<depth>3</depth>
	</size>
	<segmented>0</segmented>
	<object>
		<name>car</name>
		<pose>Unspecified</pose>
		<truncated>0</truncated>
		<difficult>0</difficult>
		<occluded>0</occluded>
		<bndbox>
			<xmin>44</xmin>
			<xmax>86</xmax>
			<ymin>28</ymin>
			<ymax>49</ymax>
		</bndbox>
	</object>
</annotation>
